exafs_neo/__init__.py
exafs_neo/_version.py
exafs_neo/exafs.py
exafs_neo/exafs_fileobj.py
exafs_neo/exafs_pop.py
exafs_neo/helper.py
exafs_neo/import_lib.py
exafs_neo/individual.py
exafs_neo/ini_parser.py
exafs_neo/input_arg.py
exafs_neo/neoCrossOver.py
exafs_neo/neoFilePars.py
exafs_neo/neoMutator.py
exafs_neo/neoPars.py
exafs_neo/neoResult.py
exafs_neo/neoSelector.py
exafs_neo/parser.py
exafs_neo/pathObj.py
exafs_neo/pathrange.py
exafs_neo/pathrange_file.py
exafs_neo/utils.py
exafs_neo-2.0.1.dist-info/LICENSE
exafs_neo-2.0.1.dist-info/METADATA
exafs_neo-2.0.1.dist-info/WHEEL
exafs_neo-2.0.1.dist-info/entry_points.txt
exafs_neo-2.0.1.dist-info/top_level.txt
exafs_neo-2.0.1.dist-info/RECORD
