Metadata-Version: 2.1
Name: exafs-neo
Version: 2.0.1
Summary: exafs_neo AI analysis using GA
Home-page: https://github.com/laumiulun/EXAFS_Neo
Download-URL: https://github.com/laumiulun/EXAFS_Neo/tarball/master
Author: Miu Lun Lau, Jeff Terry, Min Long
Author-email: andylau@u.boisestate.edu, jterry98@iit.edu, minlong@boisestate.edu
License: GPLv3
Keywords: exafs_neo,AI,analysis
License-File: LICENSE
Requires-Dist: numpy
Requires-Dist: xraylarch
Requires-Dist: attrs
Requires-Dist: matplotlib
Requires-Dist: psutil
